LICENSE
MANIFEST.in
README.md
requirements.txt
setup.cfg
setup.py
contacts/__init__.py
contacts/lib.py
contacts/feedback/__init__.py
contacts/feedback/admin.py
contacts/feedback/forms.py
contacts/feedback/models.py
contacts/feedback/urls.py
contacts/feedback/views.py
contacts/feedback/locale/en/LC_MESSAGES/django.mo
contacts/feedback/locale/en/LC_MESSAGES/django.po
contacts/feedback/locale/ru/LC_MESSAGES/django.mo
contacts/feedback/locale/ru/LC_MESSAGES/django.po
contacts/feedback/locale/uk/LC_MESSAGES/django.mo
contacts/feedback/locale/uk/LC_MESSAGES/django.po
contacts/feedback/migrations/0001_initial.py
contacts/feedback/migrations/__init__.py
contacts/feedback/static/feedback/feedback.js
contacts/feedback/templates/feedback/form.html
contacts/feedback/templates/feedback/modal.html
contacts/feedback/templates/feedback/sms.txt
contacts/feedback/templates/feedback/success_message.html
contacts/feedback/templates/feedback/view.html
contacts/feedback/templates/feedback/email/message.html
contacts/feedback/templates/feedback/email/subject.txt
contacts/return_calls/__init__.py
contacts/return_calls/admin.py
contacts/return_calls/forms.py
contacts/return_calls/models.py
contacts/return_calls/urls.py
contacts/return_calls/views.py
contacts/return_calls/widgets.py
contacts/return_calls/locale/en/LC_MESSAGES/django.mo
contacts/return_calls/locale/en/LC_MESSAGES/django.po
contacts/return_calls/locale/ru/LC_MESSAGES/django.mo
contacts/return_calls/locale/ru/LC_MESSAGES/django.po
contacts/return_calls/locale/uk/LC_MESSAGES/django.mo
contacts/return_calls/locale/uk/LC_MESSAGES/django.po
contacts/return_calls/migrations/0001_initial.py
contacts/return_calls/migrations/__init__.py
contacts/return_calls/static/return_calls/returnCall.js
contacts/return_calls/templates/return_calls/form.html
contacts/return_calls/templates/return_calls/modal.html
contacts/return_calls/templates/return_calls/sms.txt
contacts/return_calls/templates/return_calls/success_message.html
django_mp_contacts.egg-info/PKG-INFO
django_mp_contacts.egg-info/SOURCES.txt
django_mp_contacts.egg-info/dependency_links.txt
django_mp_contacts.egg-info/requires.txt
django_mp_contacts.egg-info/top_level.txt