Metadata-Version: 1.1
Name: django-mp-contacts
Version: 4.0
Summary: Django contacts app
Home-page: https://github.com/pmaigutyak/mp-contacts
Author: Paul Maigutyak
Author-email: pmaigutyak@gmail.com
License: MIT
Download-URL: https://github.com/pmaigutyak/mp-contacts/archive/4.0.tar.gz
Platform: UNKNOWN
